<?xml version="1.0" encoding="UTF-8"?>
<EFUSUB xmlns="http://aeec.aviation-ia.net/633" xmlns:xsi="http://www.w3.org/2001/XMLSchema-instance" xsi:schemaLocation="http://aeec.aviation-ia.net/633 EFF.xsd" state="New" fullPackage="true">
<M633Header versionNumber="3" timestamp="2025-05-14T14:27:55+00:00"/>
<M633SupplementaryHeader>
<Flight flightOriginDate="2025-05-14" scheduledTimeOfDeparture="2025-05-14T16:00:00Z"><FlightIdentification><FlightIdentifier>SXSTST7</FlightIdentifier><FlightNumber airlineIATACode = "XQ" number = "TST7"><CommercialFlightNumber>XQTST7</CommercialFlightNumber></FlightNumber></FlightIdentification><DepartureAirport><AirportICAOCode>LTAI</AirportICAOCode><AirportIATACode>AYT</AirportIATACode></DepartureAirport><ArrivalAirport><AirportICAOCode>EDDK</AirportICAOCode><AirportIATACode>CGN</AirportIATACode></ArrivalAirport></Flight><Aircraft aircraftRegistration="TCSMB"><AircraftModel><AircraftICAOType>B38M</AircraftICAOType></AircraftModel></Aircraft>
</M633SupplementaryHeader>
<SubFolder title="_Root_Folder_">
<SubFolder title="NOTAMS">
<Topic name="NOTAM/6.0 Crew Additional Info"/>
<Topic name="NOTAM/0.0 NOTAMS Validity"/>
<Topic name="NOTAM/1.0 All"/>
<Topic name="NOTAM/0.1 Crew Alert"/>
<Topic name="NOTAM/0.2 Crew Buletin"/>
<Document authorProfile="dispatcher" captainOnly="0" mandatory="1" originalDateTime="2025-05-14T14:27:55+00:00" priority="0" status="None" title="CrewInfo" transferPending="0" updateDateTime="2025-05-14T14:27:55+00:00" id="file1" file="CrewAdditionalInfo.txt" type="text/plain">
  <Topic name="NOTAM/6.0 Crew Additional Info"/>
</Document>
<Document authorProfile="dispatcher" captainOnly="0" mandatory="0" originalDateTime="2025-05-14T14:27:55+00:00" priority="0" status="None" title="NOTAM validity" transferPending="0" updateDateTime="2025-05-14T14:27:55+00:00" id="file2" file="NOTAM validity.txt" type="text/plain">
  <Topic name="NOTAM/0.0 NOTAMS Validity"/>
</Document>
<Document authorProfile="dispatcher" captainOnly="0" mandatory="0" originalDateTime="2025-05-14T14:27:55+00:00" priority="0" status="None" title="NOTAM XML" transferPending="0" updateDateTime="2025-05-14T14:27:55+00:00" id="file3" file="NOTAM.xml" type="text/xml">
  <Topic name="NOTAM/1.0 All"/>
</Document>
<Document authorProfile="dispatcher" captainOnly="0" mandatory="0" originalDateTime="2025-05-14T14:27:55+00:00" priority="0" status="None" title="CrewAlert" transferPending="0" updateDateTime="2025-05-14T14:27:55+00:00" id="file4" file="CrewAlert.txt" type="text/plain">
  <Topic name="NOTAM/0.1 Crew Alert"/>
</Document>
<Document authorProfile="dispatcher" captainOnly="0" mandatory="0" originalDateTime="2025-05-14T14:27:55+00:00" priority="0" status="None" title="Crew Bulletin" transferPending="0" updateDateTime="2025-05-14T14:27:55+00:00" id="file5" file="CrewBulletin.txt" type="text/plain">
  <Topic name="NOTAM/0.2 Crew Buletin"/>
</Document>
</SubFolder>
<SubFolder title="METEO">
<Topic name="Weather/General"/>
<Topic name="Weather/Airport"/>
<Topic name="Weather/Region"/>
<Topic name="Weather/Route SigWx"/>
<Topic name="Weather/Upper Winds"/>
<Topic name="Weather/Vertical Profile"/>
<Document authorProfile="dispatcher" captainOnly="0" mandatory="0" originalDateTime="2025-05-14T14:27:55+00:00" priority="0" status="None" title="Tropical Cyclone" transferPending="0" updateDateTime="2025-05-14T14:27:55+00:00" id="file6" file="TropicalCyclone.txt" type="text/plain">
  <Topic name="Weather/General"/>
</Document>
<Document authorProfile="dispatcher" captainOnly="0" mandatory="0" originalDateTime="2025-05-14T14:27:55+00:00" priority="0" status="None" title="Volcanic Ash" transferPending="0" updateDateTime="2025-05-14T14:27:55+00:00" id="file7" file="VolcanicAsh.txt" type="text/plain">
  <Topic name="Weather/General"/>
</Document>
<Document authorProfile="dispatcher" captainOnly="0" mandatory="0" originalDateTime="2025-05-14T14:27:55+00:00" priority="0" status="None" title="WX AIRPORT XML" transferPending="0" updateDateTime="2025-05-14T14:27:55+00:00" id="file8" file="AirportWeather.xml" type="text/xml">
  <Topic name="Weather/Airport"/>
</Document>
<Document authorProfile="dispatcher" captainOnly="0" mandatory="0" originalDateTime="2025-05-14T14:27:55+00:00" priority="0" status="None" title="WX REGION XML" transferPending="0" updateDateTime="2025-05-14T14:27:55+00:00" id="file9" file="RegionWeather.xml" type="text/xml">
  <Topic name="Weather/Region"/>
</Document>
<Document authorProfile="dispatcher" captainOnly="0" mandatory="0" originalDateTime="2025-05-14T14:27:55+00:00" priority="0" status="None" title="SIGWX_MED_LON_FIX_141800" transferPending="0" updateDateTime="2025-05-14T14:27:55+00:00" id="file10" file="SIGWX_MED_LON_FIX_1418.GIF" type="image/gif">
  <Topic name="Weather/Route SigWx"/>
</Document>
<Document authorProfile="dispatcher" captainOnly="0" mandatory="0" originalDateTime="2025-05-14T14:27:55+00:00" priority="0" status="None" title="UAD FL340" transferPending="0" updateDateTime="2025-05-14T14:27:55+00:00" id="file11" file="UAD_FL340.GIF" type="image/gif">
  <Topic name="Weather/Upper Winds"/>
</Document>
<Document authorProfile="dispatcher" captainOnly="0" mandatory="0" originalDateTime="2025-05-14T14:27:55+00:00" priority="0" status="None" title="UAD FL380" transferPending="0" updateDateTime="2025-05-14T14:27:55+00:00" id="file12" file="UAD_FL380.GIF" type="image/gif">
  <Topic name="Weather/Upper Winds"/>
</Document>
<Document authorProfile="dispatcher" captainOnly="0" mandatory="0" originalDateTime="2025-05-14T14:27:55+00:00" priority="0" status="None" title="UAD FL420" transferPending="0" updateDateTime="2025-05-14T14:27:55+00:00" id="file13" file="UAD_FL420.GIF" type="image/gif">
  <Topic name="Weather/Upper Winds"/>
</Document>
<Document authorProfile="dispatcher" captainOnly="0" mandatory="0" originalDateTime="2025-05-14T14:27:55+00:00" priority="0" status="None" title="Vertical Profile" transferPending="0" updateDateTime="2025-05-14T14:27:55+00:00" id="file14" file="VertProf.GIF" type="image/gif">
  <Topic name="Weather/Vertical Profile"/>
</Document>
</SubFolder>
<SubFolder title="Flight plan">
<Topic name="FlightPlan/Operational"/>
<Topic name="FlightPlan/ATCICAO"/>
<Topic name="AirportData"/>
<Topic name="AirspaceData"/>
<Topic name="UpperAirData"/>
<Document changed="New" authorProfile="dispatcher" captainOnly="0" mandatory="1" displayModel="ETOPSlayout" originalDateTime="2025-05-14T14:27:55+00:00" priority="0" status="None" title="OFP XML" transferPending="0" updateDateTime="2025-05-14T14:27:55+00:00" id="file15" file="LTAIEDDK-std.xml" type="text/xml">
  <Topic name="FlightPlan/Operational"/>
</Document>
<Document changed="New" authorProfile="dispatcher" captainOnly="0" mandatory="1" displayModel="ETOPSlayout" originalDateTime="2025-05-14T14:27:55+00:00" priority="0" status="None" title="ATC XML" transferPending="0" updateDateTime="2025-05-14T14:27:55+00:00" id="file16" file="ATCFlightPlan.xml" type="text/xml">
  <Parameter name="FilingStatus" value="not-filed"/>
  <Topic name="FlightPlan/ATCICAO"/>
</Document>
<Document changed="New" authorProfile="dispatcher" captainOnly="0" mandatory="1" originalDateTime="2025-05-14T14:27:55+00:00" priority="0" status="None" title="APTD XML" transferPending="0" updateDateTime="2025-05-14T14:27:55+00:00" id="file17" file="AirportData.xml" type="text/xml">
  <Topic name="AirportData"/>
</Document>
<Document changed="New" authorProfile="dispatcher" captainOnly="0" mandatory="1" originalDateTime="2025-05-14T14:27:55+00:00" priority="0" status="None" title="ASPD XML" transferPending="0" updateDateTime="2025-05-14T14:27:55+00:00" id="file18" file="AirspaceData.xml" type="text/xml">
  <Topic name="AirspaceData"/>
</Document>
<Document changed="New" authorProfile="dispatcher" captainOnly="0" mandatory="1" originalDateTime="2025-05-14T14:27:55+00:00" priority="0" status="None" title="UAD XML" transferPending="0" updateDateTime="2025-05-14T14:27:55+00:00" id="file19" file="UpperWindData.xml" type="text/xml">
  <Topic name="UpperAirData"/>
</Document>
</SubFolder>
<SubFolder title="BriefingId">
<Document changed="New" authorProfile="dispatcher" captainOnly="0" mandatory="0" originalDateTime="2025-05-14T14:28:28Z" priority="0" status="None" title="BriefingId" transferPending="0" updateDateTime="2025-05-14T14:28:28Z" id="BriefingId" file="briefingid.txt" type="text/xml">
  <Topic name="AirlineDefined"/>
</Document>
</SubFolder>          
<SubFolder title="Paper Flight Plan">

<Topic name="Paper Flight Plan"/>
<Document changed="New" authorProfile="dispatcher" captainOnly="0" mandatory="0" originalDateTime="2025-05-14T14:27:55+00:00" priority="0" status="None" title="Paper Flight Plan" transferPending="0" updateDateTime="2025-05-14T14:27:55+00:00" id="file20" file="Paper Flight Plan.pdf" type="application/pdf">
  <Topic name="Paper Flight Plan"/>
</Document>
</SubFolder>
<SubFolder title="RAIM Briefing">
<Topic name="RAIM Outages"/>
<Document authorProfile="dispatcher" captainOnly="0" mandatory="0" originalDateTime="2025-05-14T14:27:55+00:00" priority="0" status="None" title="RAIM Outages" transferPending="0" updateDateTime="2025-05-14T14:27:55+00:00" id="file21" file="RAIM.txt" type="text/plain">
  <Topic name="RAIM Outages"/>
</Document>
</SubFolder>
</SubFolder>
</EFUSUB>
